README.md
setup.py
pandas_sql.egg-info/PKG-INFO
pandas_sql.egg-info/SOURCES.txt
pandas_sql.egg-info/dependency_links.txt
pandas_sql.egg-info/not-zip-safe
pandas_sql.egg-info/requires.txt
pandas_sql.egg-info/top_level.txt
pd_sql/__init__.py
pd_sql/db_model.py
pd_sql/tools.py