Metadata-Version: 1.1
Name: pandas-sql
Version: 0.1.7
Summary: pandas to_sql by update, ignore or replace
Home-page: https://github.com/xbanke/pandas-sql
Author: quantpy
Author-email: quantpy@qq.com
License: MIT
Keywords: pandas,sqlalchemy
Platform: UNKNOWN
Classifier: Development Status :: 4 - Beta
Classifier: Environment :: Console
Classifier: Intended Audience :: Developers
Classifier: License :: OSI Approved :: MIT License
Classifier: Operating System :: OS Independent
Classifier: Programming Language :: Python
Classifier: Programming Language :: Python :: Implementation
Classifier: Programming Language :: Python :: 3.6
Classifier: Topic :: Software Development :: Libraries
